setup.py
sandpilemodel/__init__.py
sandpilemodel/sandpilemodel.py
sandpilemodel.egg-info/PKG-INFO
sandpilemodel.egg-info/SOURCES.txt
sandpilemodel.egg-info/dependency_links.txt
sandpilemodel.egg-info/requires.txt
sandpilemodel.egg-info/top_level.txt